tradeexecutor/__init__.py
tradeexecutor/analysis/__init__.py
tradeexecutor/analysis/alpha_model_analyser.py
tradeexecutor/analysis/fee_analyser.py
tradeexecutor/analysis/multipair.py
tradeexecutor/analysis/trade_analyser.py
tradeexecutor/backtest/__init__.py
tradeexecutor/backtest/backtest_execution.py
tradeexecutor/backtest/backtest_pricing.py
tradeexecutor/backtest/backtest_routing.py
tradeexecutor/backtest/backtest_runner.py
tradeexecutor/backtest/backtest_sync.py
tradeexecutor/backtest/backtest_valuation.py
tradeexecutor/backtest/data_preload.py
tradeexecutor/backtest/grid_search.py
tradeexecutor/backtest/notebook.py
tradeexecutor/backtest/simulated_wallet.py
tradeexecutor/cli/__init__.py
tradeexecutor/cli/approval.py
tradeexecutor/cli/bootstrap.py
tradeexecutor/cli/commands/__init__.py
tradeexecutor/cli/commands/app.py
tradeexecutor/cli/commands/check_universe.py
tradeexecutor/cli/commands/check_wallet.py
tradeexecutor/cli/commands/console.py
tradeexecutor/cli/commands/enzyme_asset_list.py
tradeexecutor/cli/commands/enzyme_deploy_vault.py
tradeexecutor/cli/commands/hello.py
tradeexecutor/cli/commands/init.py
tradeexecutor/cli/commands/perform_test_trade.py
tradeexecutor/cli/commands/repair.py
tradeexecutor/cli/commands/shared_options.py
tradeexecutor/cli/commands/start.py
tradeexecutor/cli/commands/version.py
tradeexecutor/cli/discord.py
tradeexecutor/cli/env.py
tradeexecutor/cli/latest_release.py
tradeexecutor/cli/log.py
tradeexecutor/cli/loop.py
tradeexecutor/cli/main.py
tradeexecutor/cli/result.py
tradeexecutor/cli/testtrade.py
tradeexecutor/cli/version_info.py
tradeexecutor/cli/watchdog.py
tradeexecutor/ethereum/__init__.py
tradeexecutor/ethereum/abi/uniswap/erc20.json
tradeexecutor/ethereum/abi/uniswap/factory.json
tradeexecutor/ethereum/abi/uniswap/pair.json
tradeexecutor/ethereum/abi/uniswap/uniswap_erc20.json
tradeexecutor/ethereum/enzyme/__init__.py
tradeexecutor/ethereum/enzyme/asset.py
tradeexecutor/ethereum/enzyme/polygon_assets.json
trade_executor-0.3.dist-info/WHEEL
trade_executor-0.3.dist-info/entry_points.txt
trade_executor-0.3.dist-info/LICENSE.txt
trade_executor-0.3.dist-info/METADATA
trade_executor-0.3.dist-info/RECORD
