Metadata-Version: 2.1
Name: trade-executor
Version: 0.3
Summary: Algorithmic trading backtesting and execution engine for decentralised finance
Home-page: https://tradingstrategy.ai
License: APGL
Keywords: algorithmic trading,ethereum,cryptocurrency,uniswap,quantitative finance,binance,coinbase,pancakeswap
Author: Mikko Ohtamaa
Author-email: mikko@tradingstrategy.ai
Requires-Python: >=3.10,<3.11
Classifier: License :: Other/Proprietary License
Classifier: Programming Language :: Python :: 3
Classifier: Programming Language :: Python :: 3.10
Provides-Extra: data
Provides-Extra: execution
Provides-Extra: qstrader
Provides-Extra: quantstats
Provides-Extra: web-server
Requires-Dist: APScheduler (>=3.9.1,<4.0.0) ; extra == "execution"
Requires-Dist: WebTest (>=3.0.0,<4.0.0) ; extra == "web-server"
Requires-Dist: colorama (>=0.4.4,<0.5.0) ; extra == "execution"
Requires-Dist: coloredlogs (>=15.0.1,<16.0.0) ; extra == "execution"
Requires-Dist: ipywidgets (>=7.0,<8.0)
Requires-Dist: jupyterlab (>=3.5.0,<4.0.0)
Requires-Dist: kaleido (==0.2.1) ; extra == "execution"
Requires-Dist: matplotlib (>=3.6.0,<4.0.0)
Requires-Dist: openapi-core (<0.17) ; extra == "web-server"
Requires-Dist: pandas-ta (>=0.3.14-beta.0,<0.4.0)
Requires-Dist: prompt-toolkit (>=3.0.31,<4.0.0) ; extra == "execution"
Requires-Dist: pyramid (>=2.0,<3.0) ; extra == "web-server"
Requires-Dist: pyramid-openapi3 (>=0.16.0,<0.17.0) ; extra == "web-server"
Requires-Dist: python-dotenv (>=0.21.0,<0.22.0) ; extra == "execution"
Requires-Dist: python-logging-discord-handler (>=0.1.3,<0.2.0) ; extra == "execution"
Requires-Dist: python-logstash-tradingstrategy (==0.5.1) ; extra == "execution"
Requires-Dist: quantstats (>=0.0.59,<0.0.60) ; extra == "quantstats"
Requires-Dist: requests (>=2.27.1,<3.0.0)
Requires-Dist: tblib (>=1.7.0,<2.0.0)
Requires-Dist: tqdm (>=4.64.1,<5.0.0)
Requires-Dist: tqdm-loggable (==0.1.3)
Requires-Dist: trading-strategy (==0.14)
Requires-Dist: trading-strategy-qstrader (>=0.5,<0.6) ; extra == "qstrader"
Requires-Dist: typer (>=0.4.0,<0.5.0) ; extra == "execution"
Requires-Dist: waitress (>=2.0.0,<3.0.0) ; extra == "web-server"
Requires-Dist: web3-ethereum-defi (==0.18.3) ; extra == "data"
Project-URL: Repository, https://github.com/tradingstrategy-ai/trade-executor
